hack4u_prueba/__init__.py
hack4u_prueba/courses.py
hack4u_prueba/utils.py
hack4u_prueba-0.1.4.dist-info/METADATA
hack4u_prueba-0.1.4.dist-info/WHEEL
hack4u_prueba-0.1.4.dist-info/top_level.txt
hack4u_prueba-0.1.4.dist-info/RECORD
