Metadata-Version: 2.1
Name: hack4u_prueba
Version: 0.1.4
Summary: Una biblioteca para consultar cursos
Home-page: https://jarviss
Author: J.A.R.V.I.S.
